ctp_pipeline_viewer/__init__.py
ctp_pipeline_viewer/ctp_processing.py
ctp_pipeline_viewer/data_types.py
ctp_pipeline_viewer/monitor_app.py
ctp_pipeline_viewer/xnat_processing.py
ctp_pipeline_viewer-0.0.1.dist-info/METADATA
ctp_pipeline_viewer-0.0.1.dist-info/WHEEL
ctp_pipeline_viewer-0.0.1.dist-info/entry_points.txt
ctp_pipeline_viewer-0.0.1.dist-info/top_level.txt
ctp_pipeline_viewer-0.0.1.dist-info/RECORD
